{
    "1601": {
        "name": "Betschwanden"
    },
    "1602": {
        "name": "Bilten"
    },
    "1603": {
        "name": "Braunwald"
    },
    "1604": {
        "name": "Diesbach (GL)"
    },
    "1605": {
        "name": "Elm"
    },
    "1606": {
        "name": "Engi"
    },
    "1607": {
        "name": "Ennenda"
    },
    "1608": {
        "name": "Filzbach"
    },
    "1609": {
        "name": "Glarus"
    },
    "1610": {
        "name": "Haslen"
    },
    "1611": {
        "name": "H\u00e4tzingen"
    },
    "1612": {
        "name": "Leuggelbach"
    },
    "1613": {
        "name": "Linthal"
    },
    "1614": {
        "name": "Luchsingen"
    },
    "1615": {
        "name": "Matt"
    },
    "1616": {
        "name": "Mitl\u00f6di"
    },
    "1617": {
        "name": "Mollis"
    },
    "1618": {
        "name": "M\u00fchlehorn"
    },
    "1619": {
        "name": "N\u00e4fels"
    },
    "1620": {
        "name": "Netstal"
    },
    "1621": {
        "name": "Nidfurn"
    },
    "1622": {
        "name": "Niederurnen"
    },
    "1623": {
        "name": "Oberurnen"
    },
    "1624": {
        "name": "Obstalden"
    },
    "1625": {
        "name": "Riedern"
    },
    "1626": {
        "name": "R\u00fcti (GL)"
    },
    "1627": {
        "name": "Schwanden (GL)"
    },
    "1628": {
        "name": "Schw\u00e4ndi"
    },
    "1629": {
        "name": "Sool"
    }
}